vdiff/__init__.py
vdiff/main.py
vdiff/vdiff.py
vdiff-2.6.0.dist-info/LICENSE
vdiff-2.6.0.dist-info/METADATA
vdiff-2.6.0.dist-info/WHEEL
vdiff-2.6.0.dist-info/entry_points.txt
vdiff-2.6.0.dist-info/top_level.txt
vdiff-2.6.0.dist-info/zip-safe
vdiff-2.6.0.dist-info/RECORD
