Metadata-Version: 2.1
Name: vdiff
Version: 2.6.0
Summary: Efficiently manage the differences between two files using vim.
Home-page: http://nurdletech.com/linux-utilities/vdiff
Author: Ken Kundert
Author-email: vdiff@nurdletech.com
License: GPLv3+
Download-URL: https://github.com/kenkundert/vdiff/tarball/master
Keywords: vim,diff
Platform: UNKNOWN
Classifier: Development Status :: 5 - Production/Stable
Classifier: Environment :: Console
Classifier: Intended Audience :: End Users/Desktop
Classifier: License :: OSI Approved :: GNU General Public License v3 or later (GPLv3+)
Classifier: Natural Language :: English
Classifier: Operating System :: POSIX :: Linux
Classifier: Programming Language :: Python :: 3
Classifier: Programming Language :: Python :: 3.6
Classifier: Programming Language :: Python :: 3.7
Classifier: Programming Language :: Python :: 3.8
Classifier: Programming Language :: Python :: 3.9
Classifier: Topic :: Utilities
Requires-Dist: docopt
Requires-Dist: inform (>=1.2)
Requires-Dist: shlib (>=0.8)
Requires-Dist: appdirs
